[
    {
        "week_no": 1,
        "start_date": "2018-08-05",
        "end_date": "2018-08-11",
        "id": 8,
        "is_current_week": false
    },
    {
        "week_no": 2,
        "start_date": "2018-08-12",
        "end_date": "2018-08-18",
        "id": 9,
        "is_current_week": false
    },
    {
        "week_no": 3,
        "start_date": "2018-08-26",
        "end_date": "2018-09-01",
        "id": 10,
        "is_current_week": false
    },
    {
        "week_no": 4,
        "start_date": "2018-09-02",
        "end_date": "2018-09-08",
        "id": 11,
        "is_current_week": false
    }
]